sqlalchemy_bundle_model/__init__.py
sqlalchemy_bundle_model-0.2.1.dist-info/LICENSE
sqlalchemy_bundle_model-0.2.1.dist-info/WHEEL
sqlalchemy_bundle_model-0.2.1.dist-info/METADATA
sqlalchemy_bundle_model-0.2.1.dist-info/RECORD
