Metadata-Version: 2.1
Name: sqlalchemy-bundle-model
Version: 0.2.1
Summary: An extension to SQLAlchemy to treat aggregated columns and clauses as Models
Home-page: https://github.com/yu-ichiro/sqlalchemy_bundle_model
License: Apache Licence 2.0
Author: Yuichiro Smith
Author-email: contact@yu-smith.com
Requires-Python: >=3.6,<4.0
Classifier: Development Status :: 4 - Beta
Classifier: Intended Audience :: Developers
Classifier: License :: OSI Approved :: Apache Software License
Classifier: License :: Other/Proprietary License
Classifier: Programming Language :: Python :: 3
Classifier: Programming Language :: Python :: 3.6
Classifier: Programming Language :: Python :: 3.7
Classifier: Programming Language :: Python :: 3.8
Classifier: Programming Language :: Python :: 3.9
Classifier: Topic :: Database
Classifier: Topic :: Software Development :: Libraries
Classifier: Typing :: Typed
Requires-Dist: SQLAlchemy (>=1.3.0)
Project-URL: Repository, https://github.com/yu-ichiro/sqlalchemy_bundle_model
